{"commitInfo":{"timestamp":1782694932251,"operation":"STREAMING UPDATE","operationParameters":{"outputMode":"Append","queryId":"3aed33cf-7f90-4e21-b95b-5c9a4569a380","epochId":"1"},"readVersion":0,"isolationLevel":"Serializable","isBlindAppend":true,"operationMetrics":{"numRemovedFiles":"0","numAddedFiles":"1","numOutputRows":"1","numOutputBytes":"6759"},"engineInfo":"Apache-Spark/4.0.0 Delta-Lake/4.0.0","txnId":"733952d2-ef6e-4835-abe5-1566eb667281"}}
{"txn":{"appId":"3aed33cf-7f90-4e21-b95b-5c9a4569a380","version":1,"lastUpdated":1782694932241}}
{"add":{"path":"part-00000-1803a92d-730f-435b-bf26-2db7442ef634-c000.snappy.parquet","partitionValues":{},"size":6759,"modificationTime":1782694932197,"dataChange":true,"stats":"{\"numRecords\":1,\"minValues\":{\"seller\":\"test-key-1\",\"datetimezone\":\"2026-06-29T04:02:05.464+03:00\",\"title\":\"Test Product\",\"name\":\"Test Name\",\"product_current_price\":\"100.0\",\"product_old_price\":\"120.0\",\"product_discount\":\"20.0\",\"product_url\":\"http://example.com/product\",\"product_image_url\":\"http://example.com/image.png\",\"product_seller\":\"Test Seller\",\"product_availability\":\"In Stock\",\"product_category\":\"Test Category\",\"product_subcategory\":\"Test Subcategory\",\"product_unit\":\"piece\",\"product_weight\":\"1 kg\",\"scraping_time\":\"2026-06-29T00:00:00Z\",\"timestamp_timezone\":\"UTC\",\"product_brand\":\"Test Brand\",\"product_ram\":\"8GB\",\"product_storage\":\"256GB\"},\"maxValues\":{\"seller\":\"test-key-1\",\"datetimezone\":\"2026-06-29T04:02:05.464+03:00\",\"title\":\"Test Product\",\"name\":\"Test Name\",\"product_current_price\":\"100.0\",\"product_old_price\":\"120.0\",\"product_discount\":\"20.0\",\"product_url\":\"http://example.com/product\",\"product_image_url\":\"http://example.com/image.png\",\"product_seller\":\"Test Seller\",\"product_availability\":\"In Stock\",\"product_category\":\"Test Category\",\"product_subcategory\":\"Test Subcategory\",\"product_unit\":\"piece\",\"product_weight\":\"1 kg\",\"scraping_time\":\"2026-06-29T00:00:00Z\",\"timestamp_timezone\":\"UTC\",\"product_brand\":\"Test Brand\",\"product_ram\":\"8GB\",\"product_storage\":\"256GB\"},\"nullCount\":{\"seller\":0,\"datetimezone\":0,\"title\":0,\"name\":0,\"product_current_price\":0,\"product_old_price\":0,\"product_discount\":0,\"product_url\":0,\"product_image_url\":0,\"product_seller\":0,\"product_availability\":0,\"product_category\":0,\"product_subcategory\":0,\"product_unit\":0,\"product_weight\":0,\"scraping_time\":0,\"timestamp_timezone\":0,\"product_brand\":0,\"product_ram\":0,\"product_storage\":0}}"}}
